zardoz/__init__.py
zardoz/cli.py
zardoz/database.py
zardoz/logging.py
zardoz/rolls.py
zardoz/state.py
zardoz/utils.py
zardoz/cogs/__init__.py
zardoz/cogs/history.py
zardoz/cogs/mode.py
zardoz/cogs/roll.py
zardoz/cogs/sample.py
zardoz/cogs/vars.py
zardoz/dice/__init__.py
zardoz/dice/__main__.py
zardoz/dice/command.py
zardoz/dice/constants.py
zardoz/dice/elements.py
zardoz/dice/exceptions.py
zardoz/dice/grammar.py
zardoz/dice/utilities.py
zardoz/dice/tests/__init__.py
zardoz/dice/tests/test_command.py
zardoz/dice/tests/test_elements.py
zardoz/dice/tests/test_grammar.py
zardoz/dice/tests/test_utilities.py
zardoz/mpl-kitty/__init__.py
zardoz/mpl-sixel/__init__.py
zardoz/mpl-sixel/sixel.py
zardoz/mpl-sixel/xterm.py
zardoz/sql/commands.sql
zardoz/sql/database.sql
zardoz-1.1.0.dist-info/AUTHORS.rst
zardoz-1.1.0.dist-info/LICENSE
zardoz-1.1.0.dist-info/METADATA
zardoz-1.1.0.dist-info/WHEEL
zardoz-1.1.0.dist-info/entry_points.txt
zardoz-1.1.0.dist-info/top_level.txt
zardoz-1.1.0.dist-info/RECORD
