Metadata-Version: 2.1
Name: zardoz
Version: 1.1.0
Summary: Another dice bot for discord.
Home-page: https://github.com/camillescott/zardoz
Author: Camille Scott
Author-email: cswel@ucdavis.edu
License: MIT license
Keywords: zardoz
Platform: UNKNOWN
Classifier: Development Status :: 2 - Pre-Alpha
Classifier: Intended Audience :: Developers
Classifier: License :: OSI Approved :: MIT License
Classifier: Natural Language :: English
Classifier: Programming Language :: Python :: 3
Classifier: Programming Language :: Python :: 3.5
Classifier: Programming Language :: Python :: 3.6
Classifier: Programming Language :: Python :: 3.7
Classifier: Programming Language :: Python :: 3.8
Requires-Python: >=3.6
Requires-Dist: discord.py
Requires-Dist: disputils
Requires-Dist: rich
Requires-Dist: dice
Requires-Dist: pyyaml
Requires-Dist: xdg
Requires-Dist: aiofiles
Requires-Dist: aiosql
Requires-Dist: aiosqlite
